odoo10_addon_partner_vat_unique-10.0.1.0.0.99.dev5-py2.7-nspkg.pth
odoo/addons/partner_vat_unique/README.rst
odoo/addons/partner_vat_unique/__init__.py
odoo/addons/partner_vat_unique/__manifest__.py
odoo/addons/partner_vat_unique/i18n/es.po
odoo/addons/partner_vat_unique/i18n/it.po
odoo/addons/partner_vat_unique/i18n/partner_vat_unique.pot
odoo/addons/partner_vat_unique/models/__init__.py
odoo/addons/partner_vat_unique/models/res_partner.py
odoo/addons/partner_vat_unique/static/description/icon.png
odoo/addons/partner_vat_unique/tests/__init__.py
odoo/addons/partner_vat_unique/tests/test_vat_unique.py
odoo10_addon_partner_vat_unique-10.0.1.0.0.99.dev5.dist-info/METADATA
odoo10_addon_partner_vat_unique-10.0.1.0.0.99.dev5.dist-info/RECORD
odoo10_addon_partner_vat_unique-10.0.1.0.0.99.dev5.dist-info/WHEEL
odoo10_addon_partner_vat_unique-10.0.1.0.0.99.dev5.dist-info/namespace_packages.txt
odoo10_addon_partner_vat_unique-10.0.1.0.0.99.dev5.dist-info/top_level.txt
