Metadata-Version: 2.1
Name: odoo10-addon-partner-vat-unique
Version: 10.0.1.0.0.99.dev5
Summary: Partner VAT Unique
Home-page: https://github.com/OCA/partner-contact
Author: Grant Thornton S.L.P, Odoo Community Association (OCA)
Author-email: support@odoo-community.org
License: AGPL-3
Platform: UNKNOWN
Classifier: Programming Language :: Python
Classifier: Framework :: Odoo
Classifier: License :: OSI Approved :: GNU Affero General Public License v3
Requires-Python: ~=2.7
Requires-Dist: odoo (<10.1dev,>=10.0)
